Workbook

Sheet Inputs_Results
A1: ROI Model: Current State vs Post-Install (Labor & Material Savings → NPV, IRR, Payback)
A3: Global Inputs | D3: Current State | E3: Calculated (Current) | G3: Post-Install | H3: Calculated (Post)
A4: Discount Rate | B4: 0.1 | C4: Annual Parts Goal (units) | D4: 100000 | E4: Annual Material Spend | F4: =D4*(1+D6)*D7 -> 1320000 | G4: 100000 | H4: Annual Material Spend | I4: =G4*(1+G6)*G7 -> 1224000
A5: Analysis Horizon (years) | B5: 3 | C5: Machine Uptime (%) | D5: 0.9 | E5: Annual Labor Cost | F5: =(D9*D10*D11*D12)*D13 + (D12*D15*D14) + (D16*D17) -> 167200 | G5: 0.99 | H5: Annual Labor Cost | I5: =(G9*G10*G11*G12)*G13 + (G12*G15*G14) + (G16*G17) -> 92200
A6: New Equipment Cost (Year 0) | B6: 500000 | C6: Scrap Percentage (%) | D6: 0.1 | E6: Total Operating Cost | F6: =F4+F5 -> 1487200 | G6: 0.02 | H6: Total Operating Cost | I6: =I4+I5 -> 1316200
A7: Other One-Time Costs (Year 0) | B7: 0 | C7: Material Cost per Part | D7: 12 | G7: 12
A8: Annual Maintenance Cost (Post) | B8: 0 | C8: —
A9: Salvage Value (Final Year) | B9: 0 | C9: Work Shifts | D9: 1 | G9: 1
C10: Days per Year | D10: 250 | G10: 250
C11: Hours per Shift | D11: 8 | G11: 8
A12: Annual Savings Calculation | C12: Number of Operators | D12: 2 | G12: 2
A13: Annual Material Savings | B13: =F4-I4 -> 96000 | C13: Hourly Wage per Operator | D13: 22 | G13: 22
A14: Annual Labor Savings | B14: =F5-I5 -> 75000 | C14: Overtime Rate per Hour | D14: 35 | G14: 35
A15: Total Annual Savings (before maintenance) | B15: =B13+B14 -> 171000 | C15: Annual Overtime Hours per Operator | D15: 60 | G15: 60
A16: Net Annual Savings (after maintenance) | B16: =B15-Inputs_Results!$B$8 -> 171000 | C16: Number of Technicians | D16: 1 | G16: 0
C17: Annual Cost per Technician | D17: 75000 | G17: 75000
A23: Productivity Gains (Incremental Throughput)
A24: Good Units (Current) = Parts * Uptime * (1 - Scrap) | B24: =ROUND(D4*D5*(1-D6),0) -> 81000
A25: Good Units (Post) = Parts * Uptime * (1 - Scrap) | B25: =ROUND(G4*G5*(1-G6),0) -> 97020
A26: Incremental Good Units (Post − Current) | B26: =(B25-B24) -> 16020
A27: Contribution per Additional Unit (auto) | B27: =IF(OR(B30="",B30=0,B29=""),0,B30*B29) -> 9.4619666
A28: Steady-State Annual Productivity Profit (Year 3+) | B28: =B26*B27 -> 151580.71
A29: Margin % of Material Unit Cost | B29: 0.75
A30: Variable Cost per Unit (auto from materials or method) | B30: =IF(B25<=0,0,I4/B25) -> 12.615955
A34: Selling Price per Component (auto) | B34: =IF(OR(B30="",B30=0,B29=""),"",B30*(1+B29)) -> 22.077922

Sheet Cash Flows
A1: Cash Flow Schedule
A3: Year | B3: Cash Flow | C3: Discount Factor | D3: Present Value | E3: Cumulative Cash Flow
A4: 0 | B4: =-(Inputs_Results!$B$6+Inputs_Results!$B$7) -> -500000 | C4: =IF(B4="","",1/(1+Inputs_Results!$B$4)^0) -> 1 | D4: =IF(B4="","",B4*C4) -> -500000 | E4: =IF(B4="","",B4) -> -500000
A5: 1 | B5: =IF(Inputs_Results!$B$5>=1, Inputs_Results!$B$16 + (Inputs_Results!$B$26*Inputs_Results!$B$27) + IF(Inputs_Results!$B$5=1,Inputs_Results!$B$9,0), "") -> 322580.71 | C5: =IF(B5="","",1/(1+Inputs_Results!$B$4)^1) -> 0.90909091 | D5: =IF(B5="","",B5*C5) -> 293255.19 | E5: =IF(B5="","",E4+B5) -> -177419.29
A6: 2 | B6: =IF(Inputs_Results!$B$5>=2, Inputs_Results!$B$16 + (Inputs_Results!$B$26*Inputs_Results!$B$27) + IF(Inputs_Results!$B$5=2,Inputs_Results!$B$9,0), "") -> 322580.71 | C6: =IF(B6="","",1/(1+Inputs_Results!$B$4)^2) -> 0.82644628 | D6: =IF(B6="","",B6*C6) -> 266595.62 | E6: =IF(B6="","",E5+B6) -> 145161.41
A7: 3 | B7: =IF(Inputs_Results!$B$5>=3, Inputs_Results!$B$16 + (Inputs_Results!$B$26*Inputs_Results!$B$27) + IF(Inputs_Results!$B$5=3,Inputs_Results!$B$9,0), "") -> 322580.71 | C7: =IF(B7="","",1/(1+Inputs_Results!$B$4)^3) -> 0.7513148 | D7: =IF(B7="","",B7*C7) -> 242359.66 | E7: =IF(B7="","",E6+B7) -> 467742.12
A8: 4 | B8: =IF(Inputs_Results!$B$5>=4, Inputs_Results!$B$16 + (Inputs_Results!$B$26*Inputs_Results!$B$27) + IF(Inputs_Results!$B$5=4,Inputs_Results!$B$9,0), "") | C8: =IF(B8="","",1/(1+Inputs_Results!$B$4)^4) | D8: =IF(B8="","",B8*C8) | E8: =IF(B8="","",E7+B8)
A9: 5 | B9: =IF(Inputs_Results!$B$5>=5, Inputs_Results!$B$16 + (Inputs_Results!$B$26*Inputs_Results!$B$27) + IF(Inputs_Results!$B$5=5,Inputs_Results!$B$9,0), "") | C9: =IF(B9="","",1/(1+Inputs_Results!$B$4)^5) | D9: =IF(B9="","",B9*C9) | E9: =IF(B9="","",E8+B9)
A10: 6 | B10: =IF(Inputs_Results!$B$5>=6, Inputs_Results!$B$16 + (Inputs_Results!$B$26*Inputs_Results!$B$27) + IF(Inputs_Results!$B$5=6,Inputs_Results!$B$9,0), "") | C10: =IF(B10="","",1/(1+Inputs_Results!$B$4)^6) | D10: =IF(B10="","",B10*C10) | E10: =IF(B10="","",E9+B10)
A11: 7 | B11: =IF(Inputs_Results!$B$5>=7, Inputs_Results!$B$16 + (Inputs_Results!$B$26*Inputs_Results!$B$27) + IF(Inputs_Results!$B$5=7,Inputs_Results!$B$9,0), "") | C11: =IF(B11="","",1/(1+Inputs_Results!$B$4)^7) | D11: =IF(B11="","",B11*C11) | E11: =IF(B11="","",E10+B11)
A12: 8 | B12: =IF(Inputs_Results!$B$5>=8, Inputs_Results!$B$16 + (Inputs_Results!$B$26*Inputs_Results!$B$27) + IF(Inputs_Results!$B$5=8,Inputs_Results!$B$9,0), "") | C12: =IF(B12="","",1/(1+Inputs_Results!$B$4)^8) | D12: =IF(B12="","",B12*C12) | E12: =IF(B12="","",E11+B12)
A13: 9 | B13: =IF(Inputs_Results!$B$5>=9, Inputs_Results!$B$16 + (Inputs_Results!$B$26*Inputs_Results!$B$27) + IF(Inputs_Results!$B$5=9,Inputs_Results!$B$9,0), "") | C13: =IF(B13="","",1/(1+Inputs_Results!$B$4)^9) | D13: =IF(B13="","",B13*C13) | E13: =IF(B13="","",E12+B13)
A14: 10 | B14: =IF(Inputs_Results!$B$5>=10, Inputs_Results!$B$16 + (Inputs_Results!$B$26*Inputs_Results!$B$27) + IF(Inputs_Results!$B$5=10,Inputs_Results!$B$9,0), "") | C14: =IF(B14="","",1/(1+Inputs_Results!$B$4)^10) | D14: =IF(B14="","",B14*C14) | E14: =IF(B14="","",E13+B14)
A15: 11 | B15: =IF(Inputs_Results!$B$5>=11, Inputs_Results!$B$16 + (Inputs_Results!$B$26*Inputs_Results!$B$27) + IF(Inputs_Results!$B$5=11,Inputs_Results!$B$9,0), "") | C15: =IF(B15="","",1/(1+Inputs_Results!$B$4)^11) | D15: =IF(B15="","",B15*C15) | E15: =IF(B15="","",E14+B15)
A16: 12 | B16: =IF(Inputs_Results!$B$5>=12, Inputs_Results!$B$16 + (Inputs_Results!$B$26*Inputs_Results!$B$27) + IF(Inputs_Results!$B$5=12,Inputs_Results!$B$9,0), "") | C16: =IF(B16="","",1/(1+Inputs_Results!$B$4)^12) | D16: =IF(B16="","",B16*C16) | E16: =IF(B16="","",E15+B16)
A17: 13 | B17: =IF(Inputs_Results!$B$5>=13, Inputs_Results!$B$16 + (Inputs_Results!$B$26*Inputs_Results!$B$27) + IF(Inputs_Results!$B$5=13,Inputs_Results!$B$9,0), "") | C17: =IF(B17="","",1/(1+Inputs_Results!$B$4)^13) | D17: =IF(B17="","",B17*C17) | E17: =IF(B17="","",E16+B17)
A18: 14 | B18: =IF(Inputs_Results!$B$5>=14, Inputs_Results!$B$16 + (Inputs_Results!$B$26*Inputs_Results!$B$27) + IF(Inputs_Results!$B$5=14,Inputs_Results!$B$9,0), "") | C18: =IF(B18="","",1/(1+Inputs_Results!$B$4)^14) | D18: =IF(B18="","",B18*C18) | E18: =IF(B18="","",E17+B18)
A19: 15 | B19: =IF(Inputs_Results!$B$5>=15, Inputs_Results!$B$16 + (Inputs_Results!$B$26*Inputs_Results!$B$27) + IF(Inputs_Results!$B$5=15,Inputs_Results!$B$9,0), "") | C19: =IF(B19="","",1/(1+Inputs_Results!$B$4)^15) | D19: =IF(B19="","",B19*C19) | E19: =IF(B19="","",E18+B19)
A20: 16 | B20: =IF(Inputs_Results!$B$5>=16, Inputs_Results!$B$16 + (Inputs_Results!$B$26*Inputs_Results!$B$27) + IF(Inputs_Results!$B$5=16,Inputs_Results!$B$9,0), "") | C20: =IF(B20="","",1/(1+Inputs_Results!$B$4)^16) | D20: =IF(B20="","",B20*C20) | E20: =IF(B20="","",E19+B20)
A21: 17 | B21: =IF(Inputs_Results!$B$5>=17, Inputs_Results!$B$16 + (Inputs_Results!$B$26*Inputs_Results!$B$27) + IF(Inputs_Results!$B$5=17,Inputs_Results!$B$9,0), "") | C21: =IF(B21="","",1/(1+Inputs_Results!$B$4)^17) | D21: =IF(B21="","",B21*C21) | E21: =IF(B21="","",E20+B21)
A22: 18 | B22: =IF(Inputs_Results!$B$5>=18, Inputs_Results!$B$16 + (Inputs_Results!$B$26*Inputs_Results!$B$27) + IF(Inputs_Results!$B$5=18,Inputs_Results!$B$9,0), "") | C22: =IF(B22="","",1/(1+Inputs_Results!$B$4)^18) | D22: =IF(B22="","",B22*C22) | E22: =IF(B22="","",E21+B22)
A23: 19 | B23: =IF(Inputs_Results!$B$5>=19, Inputs_Results!$B$16 + (Inputs_Results!$B$26*Inputs_Results!$B$27) + IF(Inputs_Results!$B$5=19,Inputs_Results!$B$9,0), "") | C23: =IF(B23="","",1/(1+Inputs_Results!$B$4)^19) | D23: =IF(B23="","",B23*C23) | E23: =IF(B23="","",E22+B23)
A24: 20 | B24: =IF(Inputs_Results!$B$5>=20, Inputs_Results!$B$16 + (Inputs_Results!$B$26*Inputs_Results!$B$27) + IF(Inputs_Results!$B$5=20,Inputs_Results!$B$9,0), "") | C24: =IF(B24="","",1/(1+Inputs_Results!$B$4)^20) | D24: =IF(B24="","",B24*C24) | E24: =IF(B24="","",E23+B24)
A25: 21 | B25: =IF(Inputs_Results!$B$5>=21, Inputs_Results!$B$16 + (Inputs_Results!$B$26*Inputs_Results!$B$27) + IF(Inputs_Results!$B$5=21,Inputs_Results!$B$9,0), "") | C25: =IF(B25="","",1/(1+Inputs_Results!$B$4)^21) | D25: =IF(B25="","",B25*C25) | E25: =IF(B25="","",E24+B25)
A26: 22 | B26: =IF(Inputs_Results!$B$5>=22, Inputs_Results!$B$16 + (Inputs_Results!$B$26*Inputs_Results!$B$27) + IF(Inputs_Results!$B$5=22,Inputs_Results!$B$9,0), "") | C26: =IF(B26="","",1/(1+Inputs_Results!$B$4)^22) | D26: =IF(B26="","",B26*C26) | E26: =IF(B26="","",E25+B26)
A27: 23 | B27: =IF(Inputs_Results!$B$5>=23, Inputs_Results!$B$16 + (Inputs_Results!$B$26*Inputs_Results!$B$27) + IF(Inputs_Results!$B$5=23,Inputs_Results!$B$9,0), "") | C27: =IF(B27="","",1/(1+Inputs_Results!$B$4)^23) | D27: =IF(B27="","",B27*C27) | E27: =IF(B27="","",E26+B27)
A28: 24 | B28: =IF(Inputs_Results!$B$5>=24, Inputs_Results!$B$16 + (Inputs_Results!$B$26*Inputs_Results!$B$27) + IF(Inputs_Results!$B$5=24,Inputs_Results!$B$9,0), "") | C28: =IF(B28="","",1/(1+Inputs_Results!$B$4)^24) | D28: =IF(B28="","",B28*C28) | E28: =IF(B28="","",E27+B28)
A29: 25 | B29: =IF(Inputs_Results!$B$5>=25, Inputs_Results!$B$16 + (Inputs_Results!$B$26*Inputs_Results!$B$27) + IF(Inputs_Results!$B$5=25,Inputs_Results!$B$9,0), "") | C29: =IF(B29="","",1/(1+Inputs_Results!$B$4)^25) | D29: =IF(B29="","",B29*C29) | E29: =IF(B29="","",E28+B29)
A30: 26 | B30: =IF(Inputs_Results!$B$5>=26, Inputs_Results!$B$16 + (Inputs_Results!$B$26*Inputs_Results!$B$27) + IF(Inputs_Results!$B$5=26,Inputs_Results!$B$9,0), "") | C30: =IF(B30="","",1/(1+Inputs_Results!$B$4)^26) | D30: =IF(B30="","",B30*C30) | E30: =IF(B30="","",E29+B30)
A31: 27 | B31: =IF(Inputs_Results!$B$5>=27, Inputs_Results!$B$16 + (Inputs_Results!$B$26*Inputs_Results!$B$27) + IF(Inputs_Results!$B$5=27,Inputs_Results!$B$9,0), "") | C31: =IF(B31="","",1/(1+Inputs_Results!$B$4)^27) | D31: =IF(B31="","",B31*C31) | E31: =IF(B31="","",E30+B31)
A32: 28 | B32: =IF(Inputs_Results!$B$5>=28, Inputs_Results!$B$16 + (Inputs_Results!$B$26*Inputs_Results!$B$27) + IF(Inputs_Results!$B$5=28,Inputs_Results!$B$9,0), "") | C32: =IF(B32="","",1/(1+Inputs_Results!$B$4)^28) | D32: =IF(B32="","",B32*C32) | E32: =IF(B32="","",E31+B32)
A33: 29 | B33: =IF(Inputs_Results!$B$5>=29, Inputs_Results!$B$16 + (Inputs_Results!$B$26*Inputs_Results!$B$27) + IF(Inputs_Results!$B$5=29,Inputs_Results!$B$9,0), "") | C33: =IF(B33="","",1/(1+Inputs_Results!$B$4)^29) | D33: =IF(B33="","",B33*C33) | E33: =IF(B33="","",E32+B33)
A34: 30 | B34: =IF(Inputs_Results!$B$5>=30, Inputs_Results!$B$16 + (Inputs_Results!$B$26*Inputs_Results!$B$27) + IF(Inputs_Results!$B$5=30,Inputs_Results!$B$9,0), "") | C34: =IF(B34="","",1/(1+Inputs_Results!$B$4)^30) | D34: =IF(B34="","",B34*C34) | E34: =IF(B34="","",E33+B34)
G36: Results
G37: NPV | H37: =NPV(Inputs_Results!$B$4, OFFSET(B4,1,0,Inputs_Results!$B$5,1)) + B4 -> 302210.47
G38: IRR | H38: =IRR(OFFSET(B4,0,0,Inputs_Results!$B$5+1,1)) -> 0.41969364
G39: Payback (years) | H39: =H43
G40: Simple ROI (%) | H40: =IF(B4<0,(SUM(OFFSET(B4,1,0,Inputs_Results!$B$5,1))+B4)/-B4,"") -> 0.93548423
G42: Helper: k index | H42: =MATCH(TRUE, E4:E34>=0, 0) -> #VALUE!
G43: Helper: Payback | H43: =IFERROR(IF(H42=1,0,(H42-2)+(-INDEX(E4:E34,H42-1)/INDEX(B4:B34,H42))),"")
